pretix_wirecard/__init__.py
pretix_wirecard/payment.py
pretix_wirecard/signals.py
pretix_wirecard/urls.py
pretix_wirecard/views.py
pretix_wirecard/locale/django.pot
pretix_wirecard/locale/ar/LC_MESSAGES/django.mo
pretix_wirecard/locale/ar/LC_MESSAGES/django.po
pretix_wirecard/locale/cs/LC_MESSAGES/django.mo
pretix_wirecard/locale/cs/LC_MESSAGES/django.po
pretix_wirecard/locale/da/LC_MESSAGES/django.mo
pretix_wirecard/locale/da/LC_MESSAGES/django.po
pretix_wirecard/locale/de/LC_MESSAGES/django.mo
pretix_wirecard/locale/de/LC_MESSAGES/django.po
pretix_wirecard/locale/de_Informal/.gitkeep
pretix_wirecard/locale/de_Informal/LC_MESSAGES/django.mo
pretix_wirecard/locale/de_Informal/LC_MESSAGES/django.po
pretix_wirecard/locale/es/LC_MESSAGES/django.mo
pretix_wirecard/locale/es/LC_MESSAGES/django.po
pretix_wirecard/locale/fr/LC_MESSAGES/django.mo
pretix_wirecard/locale/fr/LC_MESSAGES/django.po
pretix_wirecard/locale/it/LC_MESSAGES/django.mo
pretix_wirecard/locale/it/LC_MESSAGES/django.po
pretix_wirecard/locale/nl/LC_MESSAGES/django.mo
pretix_wirecard/locale/nl/LC_MESSAGES/django.po
pretix_wirecard/locale/nl_BE/LC_MESSAGES/django.mo
pretix_wirecard/locale/nl_BE/LC_MESSAGES/django.po
pretix_wirecard/locale/pt_BR/LC_MESSAGES/django.mo
pretix_wirecard/locale/pt_BR/LC_MESSAGES/django.po
pretix_wirecard/locale/tr/LC_MESSAGES/django.mo
pretix_wirecard/locale/tr/LC_MESSAGES/django.po
pretix_wirecard/static/pretix_wirecard/.gitkeep
pretix_wirecard/static/pretix_wirecard/js/redirect.js
pretix_wirecard/templates/pretix_wirecard/.gitkeep
pretix_wirecard/templates/pretix_wirecard/action_overpaid.html
pretix_wirecard/templates/pretix_wirecard/checkout_payment_confirm.html
pretix_wirecard/templates/pretix_wirecard/checkout_payment_form.html
pretix_wirecard/templates/pretix_wirecard/control.html
pretix_wirecard/templates/pretix_wirecard/pending.html
pretix_wirecard/templates/pretix_wirecard/redirecting.html
pretix_wirecard-0.7.0.dist-info/METADATA
pretix_wirecard-0.7.0.dist-info/RECORD
pretix_wirecard-0.7.0.dist-info/WHEEL
pretix_wirecard-0.7.0.dist-info/entry_points.txt
pretix_wirecard-0.7.0.dist-info/top_level.txt
