Metadata-Version: 2.1
Name: pretix-wirecard
Version: 0.7.0
Summary: This plugin integrates Wirecard payment methods with pretix
Home-page: https://github.com/pretix/pretix-wirecard
Author: Raphael Michel
Author-email: mail@raphaelmichel.de
License: Apache Software License
Platform: UNKNOWN
